RP3Net/__init__.py
RP3Net/rp3_main.py
RP3Net/rp3_train.py
RP3Net/fm_cfg/esm2_650m/config.json
RP3Net/fm_cfg/esm2_650m/special_tokens_map.json
RP3Net/fm_cfg/esm2_650m/tokenizer_config.json
RP3Net/fm_cfg/esm2_650m/vocab.txt
RP3Net/model/__init__.py
RP3Net/model/layers.py
RP3Net/model/model.py
RP3Net/training/__init__.py
RP3Net/training/cli.py
RP3Net/training/data.py
RP3Net/training/data_emlc.py
RP3Net/training/lm.py
RP3Net/training/lm_emlc.py
RP3Net/training/metrics.py
RP3Net/util/__init__.py
RP3Net/util/fasta.py
RP3Net/util/torch.py
RP3Net/util/util.py
rp3net-0.0.1.dist-info/licenses/LICENSE
rp3net-0.0.1.dist-info/METADATA
rp3net-0.0.1.dist-info/WHEEL
rp3net-0.0.1.dist-info/entry_points.txt
rp3net-0.0.1.dist-info/top_level.txt
rp3net-0.0.1.dist-info/RECORD
