Metadata-Version: 2.4
Name: RP3Net
Version: 0.0.1
Summary: RP3Net: Modelling of recombinant soluble protein production in E. coli
Maintainer-email: Evgeny Tankhilevich <evgeny@ebi.ac.uk>
License: MIT
Classifier: Development Status :: 3 - Alpha
Classifier: Programming Language :: Python :: 3
Classifier: Operating System :: OS Independent
Requires-Python: <4.0,>=3.10
License-File: LICENSE
Requires-Dist: torch==2.5.*
Requires-Dist: pandas
Requires-Dist: transformers==4.46.*
Requires-Dist: ml_collections
Requires-Dist: peft
Requires-Dist: tqdm
Provides-Extra: training
Requires-Dist: lightning[pytorch-extra]==2.4.*; extra == "training"
Requires-Dist: polars==1.27.*; extra == "training"
Requires-Dist: wandb; extra == "training"
Dynamic: license-file
